pycrfpp.cpython-39-x86_64-linux-gnu.so
pycrfpp.libs/libstdc++-a9383cce.so.6.0.28
pycrfpp.libs/libgcc_s-a04fdf82.so.1
pycrfpp-0.1.0.dist-info/WHEEL
pycrfpp-0.1.0.dist-info/LICENSE
pycrfpp-0.1.0.dist-info/top_level.txt
pycrfpp-0.1.0.dist-info/RECORD
pycrfpp-0.1.0.dist-info/METADATA
