Metadata-Version: 2.1
Name: pycrfpp
Version: 0.1.0
Summary: Python binding for CRF++
Author-email: Seanghay Yath <seanghay.dev@gmail.com>
Project-URL: repository, https://github.com/seanghay/pycrfpp
Classifier: Development Status :: 5 - Production/Stable
Classifier: License :: OSI Approved :: MIT License
Classifier: Operating System :: OS Independent
Classifier: Programming Language :: Python :: 3
Classifier: Programming Language :: Cython
Classifier: Topic :: Scientific/Engineering :: Artificial Intelligence
Requires-Python: >=3.7
License-File: LICENSE
